o/__init__.py
o/_utils.py
o/errors.py
o-0.0.2b2.dist-info/METADATA
o-0.0.2b2.dist-info/WHEEL
o-0.0.2b2.dist-info/top_level.txt
o-0.0.2b2.dist-info/RECORD
